MANIFEST.in
setup.py
../../version.ini
accelerated/accelerated.c
accelerated/setup.py
executables/python_hacks/modify_network.py
executables/python_hacks/shutdown_host.py
grr_response_core/__init__.py
grr_response_core/version.py
grr_response_core.egg-info/PKG-INFO
grr_response_core.egg-info/SOURCES.txt
grr_response_core.egg-info/dependency_links.txt
grr_response_core.egg-info/not-zip-safe
grr_response_core.egg-info/requires.txt
grr_response_core.egg-info/top_level.txt
grr_response_core/artifacts/README.md
grr_response_core/artifacts/__init__.py
grr_response_core/artifacts/antivirus.yaml
grr_response_core/artifacts/applications.yaml
grr_response_core/artifacts/cloud_services.yaml
grr_response_core/artifacts/config_files.yaml
grr_response_core/artifacts/containerd.yaml
grr_response_core/artifacts/database_servers.yaml
grr_response_core/artifacts/docker.yaml
grr_response_core/artifacts/esxi.yaml
grr_response_core/artifacts/file_systems.yaml
grr_response_core/artifacts/hadoop.yaml
grr_response_core/artifacts/ics.yaml
grr_response_core/artifacts/installed_module_paths.yaml
grr_response_core/artifacts/installed_modules.yaml
grr_response_core/artifacts/instant_messaging.yaml
grr_response_core/artifacts/java.yaml
grr_response_core/artifacts/kaspersky_careto.yaml
grr_response_core/artifacts/kubernetes.yaml
grr_response_core/artifacts/legacy.yaml
grr_response_core/artifacts/linux.yaml
grr_response_core/artifacts/linux_proc.yaml
grr_response_core/artifacts/linux_services.yaml
grr_response_core/artifacts/macos.yaml
grr_response_core/artifacts/makefile.py
grr_response_core/artifacts/shell.yaml
grr_response_core/artifacts/tomcat.yaml
grr_response_core/artifacts/triage.yaml
grr_response_core/artifacts/unix_common.yaml
grr_response_core/artifacts/user.yaml
grr_response_core/artifacts/webbrowser.yaml
grr_response_core/artifacts/webservers.yaml
grr_response_core/artifacts/windows.yaml
grr_response_core/artifacts/windows_dll_hijacking.yaml
grr_response_core/artifacts/wmi.yaml
grr_response_core/artifacts/local/__init__.py
grr_response_core/config/__init__.py
grr_response_core/config/acls.py
grr_response_core/config/api.py
grr_response_core/config/artifacts.py
grr_response_core/config/build.py
