Metadata-Version: 2.4
Name: grr-response-core
Version: 4.0.0.post0
Summary: GRR Rapid Response
Home-page: https://github.com/google/grr
Maintainer: GRR Development Team
Maintainer-email: grr-dev@googlegroups.com
License: Apache License, Version 2.0
Requires-Python: >=3.6
Requires-Dist: cryptography==3.4.8
Requires-Dist: distro==1.7.0
Requires-Dist: fleetspeak==0.1.12
Requires-Dist: grr-response-proto==4.0.0post0
Requires-Dist: ipaddr==2.2.0
Requires-Dist: pexpect==4.8.0
Requires-Dist: pip>=21.0.1
Requires-Dist: psutil==5.8.0
Requires-Dist: python-crontab==2.5.1
Requires-Dist: python-dateutil==2.8.2
Requires-Dist: pytz==2022.7.1
Requires-Dist: PyYAML==6.0.1
Requires-Dist: requests==2.25.1
Requires-Dist: yara-python==4.5.1
Dynamic: home-page
Dynamic: license
Dynamic: maintainer
Dynamic: maintainer-email
Dynamic: requires-dist
Dynamic: requires-python
Dynamic: summary
